eracun_generator/__init__.py
eracun_generator/builder.py
eracun_generator/core.py
eracun_generator/definitions.py
eracun_generator/definitionsV2.py
eracun_generator/utils.py
eracun_generator/envelope/__init__.py
eracun_generator/envelope/utils.py
eracun_generator-0.2.5.dist-info/LICENSE.txt
eracun_generator-0.2.5.dist-info/METADATA
eracun_generator-0.2.5.dist-info/WHEEL
eracun_generator-0.2.5.dist-info/top_level.txt
eracun_generator-0.2.5.dist-info/RECORD
