Metadata-Version: 2.1
Name: eracun-generator
Version: 0.2.5
Summary: e-SLOG e-Racun v1.6.1 and v2.0 XML generator
Home-page: https://github.com/boris-savic/python-eracun
Download-URL: https://github.com/boris-savic/python-eracun/tarball/0.2.5
Author: Boris Savic
Author-email: boris70@gmail.com
Keywords: python eracun,e-racun,e-slog
License-File: LICENSE.txt
Requires-Dist: lxml (>=4.4.1)
Requires-Dist: signxml (>=2.6.0)
